goodow/__init__.py
goodow_dataflow-0.3.0.dist-info/METADATA
goodow_dataflow-0.3.0.dist-info/WHEEL
goodow_dataflow-0.3.0.dist-info/top_level.txt
goodow_dataflow-0.3.0.dist-info/RECORD
